{
  "version": "7",
  "dialect": "sqlite",
  "entries": [
    {
      "idx": 0,
      "version": "6",
      "when": 1783978578002,
      "tag": "0000_init",
      "breakpoints": true
    },
    {
      "idx": 1,
      "version": "6",
      "when": 1784297400000,
      "tag": "0001_tracking_manual_list",
      "breakpoints": true
    },
    {
      "idx": 2,
      "version": "6",
      "when": 1784297400001,
      "tag": "0002_items_added_via",
      "breakpoints": true
    },
    {
      "idx": 3,
      "version": "6",
      "when": 1784297400002,
      "tag": "0003_tracking_favorite",
      "breakpoints": true
    }
  ]
}
